bdpabc/__init__.py
bdpabc/life.py
BDPabc-0.0.1.dist-info/LICENSE
BDPabc-0.0.1.dist-info/METADATA
BDPabc-0.0.1.dist-info/WHEEL
BDPabc-0.0.1.dist-info/top_level.txt
BDPabc-0.0.1.dist-info/RECORD
