Metadata-Version: 2.1
Name: BDPabc
Version: 0.0.1
Summary: free python games written by pygame
Home-page: https://github.com/MemoryD/mxgames
Author: Memory&Xinxin
Author-email: memory_d@foxmail.com
License: MIT
Platform: UNKNOWN
Requires-Dist: pygame (<=1.9.5)
